logs_ingestion/__init__.py
logs_ingestion/logs_adapter.py
logs_ingestion/logs_decorator.py
logs_ingestion/logs_ingestion.py
logs_ingestion/logs_record.py
logs_ingestion-0.2.5.dist-info/METADATA
logs_ingestion-0.2.5.dist-info/WHEEL
logs_ingestion-0.2.5.dist-info/RECORD
