Metadata-Version: 2.1
Name: logs-ingestion
Version: 0.2.5
Summary: Package for logging to Azure Logs Ingestion API using decorators and regular logging statements.
License: Apache
Author: Richard Kooijman
Author-email: kooijman.richard@gmail.com
Requires-Python: >=3.10,<4.0
Classifier: License :: Other/Proprietary License
Classifier: Programming Language :: Python :: 3
Classifier: Programming Language :: Python :: 3.10
Classifier: Programming Language :: Python :: 3.11
Classifier: Programming Language :: Python :: 3.12
Requires-Dist: azure-core (==1.30.1)
Requires-Dist: azure-identity (==1.15.0)
Requires-Dist: azure-monitor-ingestion (==1.0.3)
Requires-Dist: pydantic (==2.7.1)
